pyFlightAnalysis-1.1.0b0.dist-info/DESCRIPTION.rst
pyFlightAnalysis-1.1.0b0.dist-info/METADATA
pyFlightAnalysis-1.1.0b0.dist-info/RECORD
pyFlightAnalysis-1.1.0b0.dist-info/WHEEL
pyFlightAnalysis-1.1.0b0.dist-info/entry_points.txt
pyFlightAnalysis-1.1.0b0.dist-info/metadata.json
pyFlightAnalysis-1.1.0b0.dist-info/top_level.txt
pyflightanalysis/__init__.py
pyflightanalysis/analysis.py
pyflightanalysis/objloader.py
pyflightanalysis/widgets.py
pyflightanalysis/icons/info.gif
pyflightanalysis/icons/info_pressed.gif
pyflightanalysis/icons/loading.gif
pyflightanalysis/icons/open.gif
pyflightanalysis/icons/pause.jpg
pyflightanalysis/icons/play.jpg
pyflightanalysis/icons/quadrotor.gif
pyflightanalysis/icons/quadrotor_focus.gif
pyflightanalysis/icons/quadrotor_pressed.gif
pyflightanalysis/icons/readme.txt
pyflightanalysis/icons/rotor_vector.gif
pyflightanalysis/icons/rotor_vector_pressed.gif
pyflightanalysis/icons/stop.jpg
pyflightanalysis/icons/trace.gif
pyflightanalysis/icons/trace_pressed.gif
pyflightanalysis/models/drone_base.mtl
pyflightanalysis/models/drone_base.obj
pyflightanalysis/models/drone_propeller1.mtl
pyflightanalysis/models/drone_propeller1.obj
pyflightanalysis/models/drone_propeller2.mtl
pyflightanalysis/models/drone_propeller2.obj
pyflightanalysis/models/drone_propeller3.mtl
pyflightanalysis/models/drone_propeller3.obj
pyflightanalysis/models/drone_propeller4.mtl
pyflightanalysis/models/drone_propeller4.obj
pyflightanalysis/models/drone_simple.mtl
pyflightanalysis/models/drone_simple.obj
