Metadata-Version: 2.0
Name: pyFlightAnalysis
Version: 1.1.0b0
Summary: Flight log data analysis visualization tool
Home-page: https://github.com/Marxlp/pyFlightAnalysis
Author: Marx Liu
Author-email: smartlazyman@gmail.com
License: MIT
Keywords: px4 log analysis
Platform: UNKNOWN
Classifier: Development Status :: 4 - Beta
Classifier: Intended Audience :: Science/Research
Classifier: License :: OSI Approved :: MIT License
Classifier: Programming Language :: Python :: 2.7
Requires-Dist: PyOpenGL (>=3.1.0)
Requires-Dist: numpy (>=1.0.0)
Requires-Dist: pyqtgraph (>=0.10.0)
Requires-Dist: pyulog (>=0.5.0)
